{
  "db_name": "PostgreSQL",
  "query": "select * from \"user\" where ap_id = $1",
  "describe": {
    "columns": [
      {
        "ordinal": 0,
        "name": "id",
        "type_info": "Varchar"
      },
      {
        "ordinal": 1,
        "name": "ap_id",
        "type_info": "Varchar"
      },
      {
        "ordinal": 2,
        "name": "username",
        "type_info": "Varchar"
      },
      {
        "ordinal": 3,
        "name": "display_name",
        "type_info": "Varchar"
      },
      {
        "ordinal": 4,
        "name": "avatar_url",
        "type_info": "Varchar"
      },
      {
        "ordinal": 5,
        "name": "email",
        "type_info": "Varchar"
      },
      {
        "ordinal": 6,
        "name": "inbox",
        "type_info": "Varchar"
      },
      {
        "ordinal": 7,
        "name": "public_key",
        "type_info": "Varchar"
      },
      {
        "ordinal": 8,
        "name": "private_key",
        "type_info": "Varchar"
      },
      {
        "ordinal": 9,
        "name": "local",
        "type_info": "Bool"
      },
      {
        "ordinal": 10,
        "name": "followers",
        "type_info": "VarcharArray"
      },
      {
        "ordinal": 11,
        "name": "created_at",
        "type_info": "Timestamptz"
      },
      {
        "ordinal": 12,
        "name": "last_refreshed_at",
        "type_info": "Timestamptz"
      },
      {
        "ordinal": 13,
        "name": "updated_at",
        "type_info": "Timestamptz"
      }
    ],
    "parameters": {
      "Left": [
        "Text"
      ]
    },
    "nullable": [
      false,
      false,
      false,
      true,
      true,
      true,
      false,
      false,
      true,
      false,
      false,
      false,
      false,
      false
    ]
  },
  "hash": "1c5db3f87a64b5ca5adebab0c46120d2fc43d9bc9daf0dac0eaef2a19e87d770"
}
